setup.cfg
setup.py
Kerosene.egg-info/PKG-INFO
Kerosene.egg-info/SOURCES.txt
Kerosene.egg-info/dependency_links.txt
Kerosene.egg-info/pbr.json
Kerosene.egg-info/requires.txt
Kerosene.egg-info/top_level.txt
kerosene/__init__.py
kerosene/datasets/__init__.py
kerosene/datasets/binarized_mnist.py
kerosene/datasets/cifar10.py
kerosene/datasets/cifar100.py
kerosene/datasets/dataset.py
kerosene/datasets/iris.py
kerosene/datasets/mnist.py
kerosene/datasets/svhn2.py