Metadata-Version: 1.1
Name: Kerosene
Version: 0.2.0
Summary: Wrapper and downloader for fuel datasets
Home-page: https://github.com/dribnet/kerosene
Author: Tom White
Author-email: tom@sixdozen.com
License: MIT
Download-URL: https://github.com/dribnet/kerosene/tarball/0.2.0
Platform: UNKNOWN
